findPlate
