Metadata-Version: 2.1
Name: findPlate
Version: 2.0.0
Summary: A package finds the car plate
Author: Guido Xhindoli
Author-email: <mail@gmail.com>
Keywords: SDAfindPlate,findPlate,find plate
Classifier: Development Status :: 1 - Planning
Classifier: Intended Audience :: Developers
Classifier: Programming Language :: Python :: 3
Classifier: Operating System :: Unix
Classifier: Operating System :: MacOS :: MacOS X
Classifier: Operating System :: Microsoft :: Windows
